[{"ID":1,"Password":"CA4006SucksBigElephantDick"},{"ID":2,"Password":"this"},{"ID":3,"Password":"s"},{"ID":4,"Password":"test"},{"ID":5,"Password":"1"},{"ID":6,"Password":"s"},{"ID":7,"Password":"s"},{"ID":8,"Password":"s"},{"ID":9,"Password":"s"},{"ID":10,"Password":"saf"},{"ID":11,"Password":"j"},{"ID":12,"Password":"s"},{"ID":13,"Password":"s"},{"ID":14,"Password":"j"},{"ID":15,"Password":"a"},{"ID":16,"Password":"s"},{"ID":17,"Password":"s"},{"ID":18,"Password":"a"},{"ID":19,"Password":"s"},{"ID":20,"Password":"s"},{"ID":21,"Password":"s"},{"ID":22,"Password":"s"},{"ID":23,"Password":"s"},{"ID":24,"Password":"s"}]